spotify/__init__.py
spotify/api.py
spotify/enums.py
spotify/errors.py
spotify/internals.py
spotify/models.py
spotify/oauth.py
spotify/py.typed
spotify/types.py
spotify/types.pyi
spotify/utils.py
aiospotify_py-1.1.0.dist-info/LICENSE
aiospotify_py-1.1.0.dist-info/WHEEL
aiospotify_py-1.1.0.dist-info/METADATA
aiospotify_py-1.1.0.dist-info/RECORD
